ydata/core/__init__.py
ydata/core/datatype.py
ydata/core/connectors/__init__.py
ydata/core/connectors/write_mode.py
ydata/core/enum/__init__.py
ydata/core/enum/string_enum.py
ydata/core/error/__init__.py
ydata/core/error/fabric_error.py
ydata_core-0.6.0.dist-info/METADATA
ydata_core-0.6.0.dist-info/WHEEL
ydata_core-0.6.0.dist-info/top_level.txt
ydata_core-0.6.0.dist-info/RECORD
